odoo/addons/ssi_sale/README.rst
odoo/addons/ssi_sale/__init__.py
odoo/addons/ssi_sale/__manifest__.py
odoo/addons/ssi_sale/hooks.py
odoo/addons/ssi_sale/data/approval_template_data.xml
odoo/addons/ssi_sale/data/ir_sequence_data.xml
odoo/addons/ssi_sale/data/policy_template_data.xml
odoo/addons/ssi_sale/data/sale_order_type.xml
odoo/addons/ssi_sale/data/sequence_template_data.xml
odoo/addons/ssi_sale/models/__init__.py
odoo/addons/ssi_sale/models/sale_order.py
odoo/addons/ssi_sale/models/sale_order_line.py
odoo/addons/ssi_sale/models/sale_order_type.py
odoo/addons/ssi_sale/security/ir.model.access.csv
odoo/addons/ssi_sale/security/ir_module_category_data.xml
odoo/addons/ssi_sale/security/res_group_data.xml
odoo/addons/ssi_sale/static/description/icon.png
odoo/addons/ssi_sale/views/crm_tag_views.xml
odoo/addons/ssi_sale/views/crm_team_views.xml
odoo/addons/ssi_sale/views/mail_activity_type_views.xml
odoo/addons/ssi_sale/views/product_attribute_views.xml
odoo/addons/ssi_sale/views/res_partner_views.xml
odoo/addons/ssi_sale/views/sale_order_template_views.xml
odoo/addons/ssi_sale/views/sale_order_type_views.xml
odoo/addons/ssi_sale/views/sale_order_views.xml
odoo/addons/ssi_sale/wizard/__init__.py
odoo/addons/ssi_sale/wizard/sale_advance_payment_inv.py
odoo14_addon_ssi_sale-14.0.5.17.0.dist-info/METADATA
odoo14_addon_ssi_sale-14.0.5.17.0.dist-info/WHEEL
odoo14_addon_ssi_sale-14.0.5.17.0.dist-info/top_level.txt
odoo14_addon_ssi_sale-14.0.5.17.0.dist-info/RECORD
