Metadata-Version: 2.1
Name: odoo14-addon-ssi_sale
Version: 14.0.5.17.0
Summary: Sale
Home-page: https://simetri-sinergi.id
Author: PT. Simetri Sinergi Indonesia, OpenSynergy Indonesia
License: AGPL-3
Classifier: Programming Language :: Python
Classifier: Framework :: Odoo
Classifier: Framework :: Odoo :: 14.0
Classifier: License :: OSI Approved :: GNU Affero General Public License v3
Requires-Python: >=3.6
Requires-Dist: odoo14-addon-sale-order-price-recalculation
Requires-Dist: odoo14-addon-ssi-m2o-configurator-mixin
Requires-Dist: odoo14-addon-ssi-master-data-mixin
Requires-Dist: odoo14-addon-ssi-multiple-approval-mixin
Requires-Dist: odoo14-addon-ssi-policy-mixin
Requires-Dist: odoo14-addon-ssi-sequence-mixin
Requires-Dist: odoo<14.1dev,>=14.0a
